cal/__init__.py
cal/a1.py
cal/a2.py
cal/a3.py
tcalbyjiyatus-0.0.4.dist-info/LICENSE
tcalbyjiyatus-0.0.4.dist-info/METADATA
tcalbyjiyatus-0.0.4.dist-info/WHEEL
tcalbyjiyatus-0.0.4.dist-info/top_level.txt
tcalbyjiyatus-0.0.4.dist-info/RECORD
