Metadata-Version: 2.1
Name: tcalbyjiyatus
Version: 0.0.4
Summary: tushar
Author: t
Author-email: tushar2010@outlook.com
Keywords: arithmetic,math,mathematics,python tutorial,avi upadhyay
Classifier: Development Status :: 1 - Planning
Classifier: Intended Audience :: Developers
Classifier: Programming Language :: Python :: 3
Classifier: Operating System :: Unix
Classifier: Operating System :: MacOS :: MacOS X
Classifier: Operating System :: Microsoft :: Windows
License-File: LICENSE
